financial_metrics/__init_.py
financial_metrics/__main__.py
financial_metrics/financial_metrics.py
financial_metrics_bertollo-0.1.2.dist-info/METADATA
financial_metrics_bertollo-0.1.2.dist-info/WHEEL
financial_metrics_bertollo-0.1.2.dist-info/entry_points.txt
financial_metrics_bertollo-0.1.2.dist-info/top_level.txt
financial_metrics_bertollo-0.1.2.dist-info/RECORD
